qmate/Queue.py
qmate/__init__.py
qmate-0.0.2.dist-info/METADATA
qmate-0.0.2.dist-info/WHEEL
qmate-0.0.2.dist-info/top_level.txt
qmate-0.0.2.dist-info/RECORD
