Metadata-Version: 2.2
Name: qmate
Version: 0.0.2
Summary: Create asynchronous and asynchronous task
Author: Digital Kelvin
Author-email: <qmate@digitalkelvin.com>
Keywords: events,tasks,queue,schedules,scheduling,event loops
Dynamic: author
Dynamic: author-email
Dynamic: description
Dynamic: description-content-type
Dynamic: keywords
Dynamic: summary
